LICENSE
MANIFEST.in
README.md
pyproject.toml
setup.cfg
setup.py
tests/__init__.py
tests/testapp/__init__.py
tests/testapp/manage.py
tests/testapp/core/__init__.py
tests/testapp/core/tests.py
tests/testapp/core/migrations/__init__.py
tests/testapp/testapp/__init__.py
tests/testapp/testapp/asgi.py
tests/testapp/testapp/settings.py
tests/testapp/testapp/urls.py
tests/testapp/testapp/wsgi.py
wagtail_panels/__init__.py
wagtail_panels/apps.py
wagtail_panels/settings.py
wagtail_panels/tests.py
wagtail_panels.egg-info/PKG-INFO
wagtail_panels.egg-info/SOURCES.txt
wagtail_panels.egg-info/dependency_links.txt
wagtail_panels.egg-info/requires.txt
wagtail_panels.egg-info/top_level.txt
wagtail_panels/migrations/__init__.py
wagtail_panels/migrations/__pycache__/__init__.cpython-311.pyc
wagtail_panels/models/__init__.py
wagtail_panels/models/reading_time.py
wagtail_panels/panels/__init__.py
wagtail_panels/panels/buttons.py
wagtail_panels/panels/reading_time.py
wagtail_panels/static/wagtail_panels/panels/reading_time/reading_time.css
wagtail_panels/static/wagtail_panels/panels/reading_time/reading_time.js
wagtail_panels/templates/wagtail_panels/panels/buttons/button.html
wagtail_panels/templates/wagtail_panels/panels/buttons/buttons.html
wagtail_panels/templates/wagtail_panels/panels/buttons/download_panel.html
wagtail_panels/templates/wagtail_panels/panels/reading_time/reading_time.html
wagtail_panels/wagtail_hooks/__init__.py
wagtail_panels/wagtail_hooks/download_panel.py